client/__init__.py
client/api/__init__.py
client/api/notebook.py
okgrade/__init__.py
okgrade/doctest.py
okgrade/grader.py
okgrade/notebook.py
okgrade/result.py
okgrade/utils.py
okgrade-0.4.3.dist-info/METADATA
okgrade-0.4.3.dist-info/RECORD
okgrade-0.4.3.dist-info/WHEEL
okgrade-0.4.3.dist-info/top_level.txt
