Metadata-Version: 2.1
Name: okgrade
Version: 0.4.3
Summary: Simple alternative to okpy for grading only
Home-page: UNKNOWN
Author: Yuvi Panda
Author-email: yuvipanda@gmail.com
License: 3-clause BSD
Platform: UNKNOWN
